logsensei/__init__.py
logsensei/constant.py
logsensei/utils.py
logsensei-1.0.0.dist-info/LICENSE
logsensei-1.0.0.dist-info/WHEEL
logsensei-1.0.0.dist-info/METADATA
logsensei-1.0.0.dist-info/RECORD
