Metadata-Version: 2.1
Name: logsensei
Version: 1.0.0
Summary: Personal Formatting on Loguru
Home-page: https://github.com/AdityaSidharta/logsensei
License: UNKNOWN
Author: Aditya Kelvianto Sidharta
Author-email: aditya.sdrt@gmail.com
Classifier: License :: OSI Approved :: MIT License
Classifier: Programming Language :: Python :: 3
Classifier: Topic :: Software Development :: Libraries :: Python Modules
Requires-Dist: loguru
Requires-Dist: scikit-learn
Requires-Dist: numpy
Requires-Dist: pandas
